wlgenlib/__init__.py
wlgenlib/api/__init__.py
wlgenlib/api/api.py
wlgenlib/core/__init__.py
wlgenlib/core/blocks.py
wlgenlib/core/config.json
wlgenlib/core/resourcemanager.py
wlgenlib/core/tasks.py
wlgenlib/core/wlgen.py
wlgenlib-1.0.dist-info/LICENSE.txt
wlgenlib-1.0.dist-info/METADATA
wlgenlib-1.0.dist-info/WHEEL
wlgenlib-1.0.dist-info/top_level.txt
wlgenlib-1.0.dist-info/RECORD
